dtit/__init__.py
dtit/dtit.py
dtit-1.2.0.dist-info/DESCRIPTION.rst
dtit-1.2.0.dist-info/METADATA
dtit-1.2.0.dist-info/RECORD
dtit-1.2.0.dist-info/WHEEL
dtit-1.2.0.dist-info/metadata.json
dtit-1.2.0.dist-info/top_level.txt
