Metadata-Version: 2.0
Name: dtit
Version: 1.2.0
Summary: A decision-tree based conditional independence test
Home-page: https://github.com/kjchalup/dtit
Author: Krzysztof Chalupka
Author-email: janchatko@gmail.com
License: MIT
Keywords: machine learning statistics decision trees
Platform: UNKNOWN
Classifier: Development Status :: 3 - Alpha
Classifier: Intended Audience :: Science/Research
Classifier: Topic :: Scientific/Engineering :: Artificial Intelligence
Classifier: License :: OSI Approved :: MIT License
Classifier: Programming Language :: Python :: 2
Classifier: Programming Language :: Python :: 2.7
Classifier: Programming Language :: Python :: 3
Classifier: Programming Language :: Python :: 3.3
Classifier: Programming Language :: Python :: 3.4
Classifier: Programming Language :: Python :: 3.5
Requires-Dist: joblib
Requires-Dist: numpy
Requires-Dist: scipy
Requires-Dist: sklearn
